c2cciutils/__init__.py
c2cciutils/applications-versions.yaml
c2cciutils/applications.yaml
c2cciutils/applications_definition.py
c2cciutils/branches.graphql
c2cciutils/commits.graphql
c2cciutils/configuration.py
c2cciutils/default_branch.graphql
c2cciutils/env.py
c2cciutils/lib/docker.py
c2cciutils/lib/oidc.py
c2cciutils/package-lock.json
c2cciutils/package.json
c2cciutils/publish.py
c2cciutils/schema-applications.json
c2cciutils/schema.json
c2cciutils/scripts/__init__.py
c2cciutils/scripts/clean.py
c2cciutils/scripts/docker_logs.py
c2cciutils/scripts/docker_versions_gen.py
c2cciutils/scripts/download_applications.py
c2cciutils/scripts/env.py
c2cciutils/scripts/k8s/__init__.py
c2cciutils/scripts/k8s/db.py
c2cciutils/scripts/k8s/install.py
c2cciutils/scripts/k8s/logs.py
c2cciutils/scripts/k8s/wait.py
c2cciutils/scripts/main.py
c2cciutils/scripts/pin_pipenv.py
c2cciutils/scripts/publish.py
c2cciutils/scripts/trigger_image_update.py
c2cciutils/scripts/version.py
c2cciutils-1.7.4.dist-info/LICENSE
c2cciutils-1.7.4.dist-info/METADATA
c2cciutils-1.7.4.dist-info/WHEEL
c2cciutils-1.7.4.dist-info/entry_points.txt
c2cciutils-1.7.4.dist-info/RECORD
