Metadata-Version: 2.1
Name: c2cciutils
Version: 1.7.4
Summary: Common utilities for Camptocamp CI
Home-page: https://github.com/camptocamp/c2cciutils
License: FreeBSD
Keywords: ci
Author: Camptocamp
Author-email: info@camptocamp.com
Requires-Python: >=3.9,<4.0
Classifier: Development Status :: 5 - Production/Stable
Classifier: Environment :: Console
Classifier: Intended Audience :: Developers
Classifier: License :: OSI Approved :: MIT License
Classifier: License :: Other/Proprietary License
Classifier: Operating System :: OS Independent
Classifier: Programming Language :: Python
Classifier: Programming Language :: Python :: 3
Classifier: Programming Language :: Python :: 3.9
Classifier: Programming Language :: Python :: 3.10
Classifier: Programming Language :: Python :: 3.11
Classifier: Programming Language :: Python :: 3.12
Classifier: Programming Language :: Python :: 3.13
Classifier: Typing :: Typed
Provides-Extra: audit
Provides-Extra: checks
Provides-Extra: pr-checks
Provides-Extra: publish
Provides-Extra: publish-plugins
Provides-Extra: version
Requires-Dist: PyYAML (>=6.0.0,<7.0.0)
Requires-Dist: debian-inspector (>=31.0.0,<32.0.0)
Requires-Dist: defusedxml (>=0.0.0,<1.0.0)
Requires-Dist: google-api-python-client (>=2.0.0,<3.0.0) ; extra == "publish"
Requires-Dist: google-auth-httplib2 (>=0.0.0,<1.0.0) ; extra == "publish"
Requires-Dist: google-auth-oauthlib (>=1.0.0,<2.0.0) ; extra == "publish"
Requires-Dist: id (>=1.0.0,<2.0.0) ; extra == "publish"
Requires-Dist: multi-repo-automation (>=1.0.0,<2.0.0) ; extra == "version"
Requires-Dist: requests (>=2.0.0,<3.0.0)
Requires-Dist: ruamel.yaml (>=0.0.0,<1.0.0)
Requires-Dist: security-md (<=2)
Requires-Dist: twine (>=5.0.0,<6.0.0) ; extra == "publish"
Project-URL: Repository, https://github.com/camptocamp/c2cciutils
